aioipapi/__init__.py
aioipapi/_client.py
aioipapi/_config.py
aioipapi/_constants.py
aioipapi/_exceptions.py
aioipapi/_logging.py
aioipapi/_utils.py
changelog.md
aioipapi-0.1.3.dist-info/LICENSE
aioipapi-0.1.3.dist-info/WHEEL
aioipapi-0.1.3.dist-info/METADATA
aioipapi-0.1.3.dist-info/RECORD
