Metadata-Version: 2.1
Name: aioipapi
Version: 0.1.3
Summary: Asynchronous aiohttp based client for https://ip-api.com
Home-page: https://github.com/espdev/aioipapi
License: MIT
Keywords: ipapi,ip-api,geoip,geo-ip,geolocation,geolocation-api
Author: Eugene Prilepin
Author-email: esp.home@gmail.com
Requires-Python: >=3.6,<4.0
Classifier: Development Status :: 4 - Beta
Classifier: License :: OSI Approved :: MIT License
Classifier: Programming Language :: Python :: 3
Classifier: Programming Language :: Python :: 3.6
Classifier: Programming Language :: Python :: 3.7
Classifier: Programming Language :: Python :: 3.8
Requires-Dist: aiohttp (>=3.6.2,<4.0.0)
Requires-Dist: aioitertools (>=0.7.0,<0.8.0)
Requires-Dist: importlib_metadata (>=2.0.0,<3.0.0)
Requires-Dist: pydantic (>=1.6.1,<2.0.0)
Requires-Dist: tenacity (>=6.2.0,<7.0.0)
Requires-Dist: yarl (>=1.5.1,<2.0.0)
Project-URL: Documentation, https://aioipapi.readthedocs.io/en/latest
Project-URL: Repository, https://github.com/espdev/aioipapi
